[
    {
    "reaction_id": "ord-9bf3202b43844610852c9d67408e26a0",
    "procedure_text": "A solution of 0.55 g (1.6 mmol) (S)-7-amino-5-(4-methoxy-benzyl)-5H,7H-dibenzo[b,d]azepin-6-one, 3.74 ml (50 mmol) trifluoroacetic acid and 1.4 ml (16 mmol) trifluormethane sulfonic acid in 38 ml dichloromethane was stirred at room temperature for 4 hours. The solvent was distilled off and extraction with aqueous sodium bicarbonate solution/ethyl acetate followed by chromatography on silicagel with ethylacetate/methanol (100-95/0-5) yielded 0.35 g (96%) (S)-7-amino-5H,7H-dibenzo[b,d]azepin-6-one as orange solid; MS: m/e: 225.4 (M+H+).",
    "reference_string": "{\"inputs\": {\"m1_m2_m3_m4\": {\"components\": [{\"identifiers\": [{\"type\": \"NAME\", \"value\": \"(S)-7-amino-5-(4-methoxy-benzyl)-5H,7H-dibenzo[b,d]azepin-6-one\"}], \"amount\": {\"mass\": {\"value\": 0.55, \"units\": \"GRAM\"}}, \"reaction_role\": \"REACTANT\"}, {\"identifiers\": [{\"type\": \"NAME\", \"value\": \"trifluoroacetic acid\"}], \"amount\": {\"volume\": {\"value\": 3.74, \"units\": \"MILLILITER\"}}, \"reaction_role\": \"REACTANT\"}, {\"identifiers\": [{\"type\": \"NAME\", \"value\": \"trifluormethane sulfonic acid\"}], \"amount\": {\"volume\": {\"value\": 1.4, \"units\": \"MILLILITER\"}}, \"reaction_role\": \"REACTANT\"}, {\"identifiers\": [{\"type\": \"NAME\", \"value\": \"dichloromethane\"}], \"amount\": {\"volume\": {\"value\": 38.0, \"units\": \"MILLILITER\"}}, \"reaction_role\": \"SOLVENT\"}]}}, \"conditions\": {\"conditions_are_dynamic\": true}, \"workups\": [{\"type\": \"DISTILLATION\", \"details\": \"The solvent was distilled off\"}, {\"type\": \"EXTRACTION\", \"details\": \"extraction with aqueous sodium bicarbonate solution/ethyl acetate\", \"input\": {\"components\": [{\"identifiers\": [{\"type\": \"NAME\", \"value\": \"sodium bicarbonate\"}], \"reaction_role\": \"WORKUP\"}, {\"identifiers\": [{\"type\": \"NAME\", \"value\": \"ethyl acetate\"}], \"reaction_role\": \"WORKUP\"}]}}], \"outcomes\": [{\"products\": [{\"identifiers\": [{\"type\": \"NAME\", \"value\": \"(S)-7-amino-5H,7H-dibenzo[b,d]azepin-6-one\"}], \"measurements\": [{\"type\": \"AMOUNT\", \"details\": \"MASS\", \"amount\": {\"mass\": {\"value\": 0.35, \"units\": \"GRAM\"}}}, {\"type\": \"YIELD\", \"details\": \"PERCENTYIELD\", \"percentage\": {\"value\": 96.0}}], \"isolated_color\": \"orange\", \"texture\": {\"type\": \"CUSTOM\", \"details\": \"solid\"}, \"reaction_role\": \"PRODUCT\"}]}]}"
    },
    {
      "reaction_id": "ord-b221295cc29747928e2b5e4962a4d7fe",
      "procedure_text": "A solution of but-3-ynyl 4-methylbenzenesulfonate (2.0 mL) and piperazine (2.0 g) in EtOH (6 mL) was heated to reflux for 30 min. The mixture was concentrated, diluted with NaOH 2 M (8 mL) and extracted with Et2O (50 mL). Evaporation of the organic layer gave a 2:1 mixture of mono and bis-alkylated piperazine (450 mg) which was discarded. The aqueous layer was further extracted with DCM (100 mL) to give of 1-(but-3-ynyl)piperazine (640 mg).",
      "reference_string": "{\"inputs\": {\"m1_m2_m4\": {\"components\": [{\"identifiers\": [{\"type\": \"NAME\", \"value\": \"but-3-ynyl 4-methylbenzenesulfonate\"}], \"amount\": {\"volume\": {\"value\": 2.0, \"units\": \"MILLILITER\"}}, \"reaction_role\": \"REACTANT\"}, {\"identifiers\": [{\"type\": \"NAME\", \"value\": \"piperazine\"}], \"amount\": {\"mass\": {\"value\": 2.0, \"units\": \"GRAM\"}}, \"reaction_role\": \"REACTANT\"}, {\"identifiers\": [{\"type\": \"NAME\", \"value\": \"EtOH\"}], \"amount\": {\"volume\": {\"value\": 6.0, \"units\": \"MILLILITER\"}}, \"reaction_role\": \"SOLVENT\"}]}, \"m3\": {\"components\": [{\"identifiers\": [{\"type\": \"NAME\", \"value\": \"mono and bis-alkylated piperazine\"}], \"amount\": {\"mass\": {\"value\": 450.0, \"units\": \"MILLIGRAM\"}}, \"reaction_role\": \"REACTANT\"}]}}, \"conditions\": {\"conditions_are_dynamic\": true}, \"workups\": [{\"type\": \"TEMPERATURE\", \"details\": \"to reflux for 30 min\", \"duration\": {\"value\": 30.0, \"units\": \"MINUTE\"}}, {\"type\": \"CONCENTRATION\", \"details\": \"The mixture was concentrated\"}, {\"type\": \"ADDITION\", \"details\": \"diluted with NaOH 2 M (8 mL)\", \"input\": {\"components\": [{\"identifiers\": [{\"type\": \"NAME\", \"value\": \"NaOH\"}], \"amount\": {\"volume\": {\"value\": 8.0, \"units\": \"MILLILITER\"}}, \"reaction_role\": \"WORKUP\"}]}}, {\"type\": \"EXTRACTION\", \"details\": \"extracted with Et2O (50 mL)\", \"input\": {\"components\": [{\"identifiers\": [{\"type\": \"NAME\", \"value\": \"Et2O\"}], \"amount\": {\"volume\": {\"value\": 50.0, \"units\": \"MILLILITER\"}}, \"reaction_role\": \"WORKUP\"}]}}, {\"type\": \"CUSTOM\", \"details\": \"Evaporation of the organic layer\"}, {\"type\": \"CUSTOM\", \"details\": \"gave\"}, {\"type\": \"EXTRACTION\", \"details\": \"The aqueous layer was further extracted with DCM (100 mL)\", \"input\": {\"components\": [{\"identifiers\": [{\"type\": \"NAME\", \"value\": \"DCM\"}], \"amount\": {\"volume\": {\"value\": 100.0, \"units\": \"MILLILITER\"}}, \"reaction_role\": \"WORKUP\"}]}}], \"outcomes\": [{\"products\": [{\"identifiers\": [{\"type\": \"NAME\", \"value\": \"1-(but-3-ynyl)piperazine\"}], \"measurements\": [{\"type\": \"AMOUNT\", \"details\": \"MASS\", \"amount\": {\"mass\": {\"value\": 640.0, \"units\": \"MILLIGRAM\"}}}], \"reaction_role\": \"PRODUCT\"}]}]}"
    },
    {
      "reaction_id": "ord-d432ba8bbc154479bc98b34ef7661589",
      "procedure_text": "A mixture of 5.6 g of 1-(6-iodohexyl)-2,3-bis(phenylmethoxy) benzene, 2.1 g of 3-chloro-4-hydroxybenzoic acid methyl ester and 5.0 g of potassium carbonate in 50 mL of acetone was stirred at reflux for 20 hours. Workup as in Example 16, chromatography on 100 g of silica gel using 15% ethyl acetate-hexane and crystallization from ethyl acetate-hexane gave 3.7 g (59% yield), mp 68\u00b0-69\u00b0, 3-chloro-4-[6-[2,3-bis(phenylmethoxy)phenyl]hexyloxy]benzoic acid methyl ester.",
      "reference_string": "{\"inputs\": {\"m1_m2_m3_m4\": {\"components\": [{\"identifiers\": [{\"type\": \"NAME\", \"value\": \"1-(6-iodohexyl)-2,3-bis(phenylmethoxy) benzene\"}], \"amount\": {\"mass\": {\"value\": 5.6, \"units\": \"GRAM\"}}, \"reaction_role\": \"REACTANT\"}, {\"identifiers\": [{\"type\": \"NAME\", \"value\": \"3-chloro-4-hydroxybenzoic acid methyl ester\"}], \"amount\": {\"mass\": {\"value\": 2.1, \"units\": \"GRAM\"}}, \"reaction_role\": \"REACTANT\"}, {\"identifiers\": [{\"type\": \"NAME\", \"value\": \"potassium carbonate\"}], \"amount\": {\"mass\": {\"value\": 5.0, \"units\": \"GRAM\"}}, \"reaction_role\": \"REACTANT\"}, {\"identifiers\": [{\"type\": \"NAME\", \"value\": \"acetone\"}], \"amount\": {\"volume\": {\"value\": 50.0, \"units\": \"MILLILITER\"}}, \"reaction_role\": \"SOLVENT\"}]}}, \"conditions\": {\"stirring\": {\"type\": \"CUSTOM\", \"details\": \"was stirred\"}, \"conditions_are_dynamic\": true}, \"workups\": [{\"type\": \"TEMPERATURE\", \"details\": \"at reflux for 20 hours\", \"duration\": {\"value\": 20.0, \"units\": \"HOUR\"}}, {\"type\": \"CUSTOM\", \"details\": \"Workup as in Example 16, chromatography on 100 g of silica gel using 15% ethyl acetate-hexane and crystallization from ethyl acetate-hexane\", \"input\": {\"components\": [{\"identifiers\": [{\"type\": \"NAME\", \"value\": \"ethyl acetate hexane\"}], \"reaction_role\": \"WORKUP\"}]}}], \"outcomes\": [{\"products\": [{\"identifiers\": [{\"type\": \"NAME\", \"value\": \"3-chloro-4-[6-[2,3-bis(phenylmethoxy)phenyl]hexyloxy]benzoic acid methyl ester\"}], \"measurements\": [{\"type\": \"YIELD\", \"details\": \"PERCENTYIELD\", \"percentage\": {\"value\": 59.0}}], \"reaction_role\": \"PRODUCT\"}]}]}"
    }
]
